MANIFEST.in
README.md
setup.py
tinker_access_client/AutoUpdateTimer.py
tinker_access_client/Client.py
tinker_access_client/ClientDaemon.py
tinker_access_client/ClientLogger.py
tinker_access_client/ClientOption.py
tinker_access_client/ClientOptionParser.py
tinker_access_client/Command.py
tinker_access_client/CommandExecutor.py
tinker_access_client/CommandHandler.py
tinker_access_client/ContextFilter.py
tinker_access_client/DeviceApi.py
tinker_access_client/I2CApi.py
tinker_access_client/LcdApi.py
tinker_access_client/LoggedRequest.py
tinker_access_client/PackageInfo.py
tinker_access_client/Service.py
tinker_access_client/ServiceInstaller.py
tinker_access_client/State.py
tinker_access_client/TinkerAccessServerApi.py
tinker_access_client/UnauthorizedAccessException.py
tinker_access_client/UserRegistrationException.py
tinker_access_client/__init__.py
tinker_access_client/lcdModule.py
tinker_access_client/version.py
tinker_access_client.egg-info/PKG-INFO
tinker_access_client.egg-info/SOURCES.txt
tinker_access_client.egg-info/dependency_links.txt
tinker_access_client.egg-info/entry_points.txt
tinker_access_client.egg-info/not-zip-safe
tinker_access_client.egg-info/requires.txt
tinker_access_client.egg-info/top_level.txt