Metadata-Version: 1.1
Name: tinker-access-client
Version: 2022.8.3.32
Summary: tinker-access-client
Home-page: http://github.com/tinkerMill/tinkerAccess
Author: TinkerMill
Author-email: devteam@tinkermill.org
License: UNKNOWN
Download-URL: https://github.com/tinkerAccess/archive/v2022.08.03.32.tar.gz
Platform: UNKNOWN
